leglag/__init__.py
leglag/dft.py
leglag/dispersion.py
leglag/moller_plesset.cpython-39-darwin.so
leglag/one_d_domain.py
leglag/one_d_molecule.py
leglag/one_e_integrals.py
leglag/two_e_integrals.cpython-39-darwin.so
leglag/utilities.cpython-39-darwin.so
leglag/integral_data/LLLLquasi_integrals.dat
leglag/integral_data/LL_bound.dat
leglag/integral_data/LL_p_bound.dat
leglag/integral_data/PP_bound.dat
leglag/integral_data/PP_n_bound.dat
leglag/integral_data/PP_p_bound.dat
leglag-0.1.0.dist-info/LICENSE
leglag-0.1.0.dist-info/METADATA
leglag-0.1.0.dist-info/WHEEL
leglag-0.1.0.dist-info/top_level.txt
leglag-0.1.0.dist-info/RECORD
