Metadata-Version: 2.1
Name: leglag
Version: 0.1.0
Summary: LegLag is an electronic structure package for 1D molecules
Home-page: https://github.com/calebball/leglag
Author: Caleb Ball
Author-email: caleb.ball@explain.com.au
License: UNKNOWN
Platform: UNKNOWN
Classifier: Programming Language :: Python :: 3
Classifier: Programming Language :: Python :: 3.9
Classifier: Programming Language :: Cython
Classifier: License :: OSI Approved :: GNU General Public License v3 (GPLv3)
Requires-Dist: numpy
Requires-Dist: scipy
